emscraper/__init__.py
emscraper/app.py
emscraper-0.1.1.dist-info/LICENSE
emscraper-0.1.1.dist-info/METADATA
emscraper-0.1.1.dist-info/WHEEL
emscraper-0.1.1.dist-info/top_level.txt
emscraper-0.1.1.dist-info/RECORD
